<T3DataStructure>
	<sheets>
		<sDEF>
			<ROOT>
				<TCEforms>
					<sheetTitle>Options</sheetTitle>
				</TCEforms>
				<type>array</type>
				<el>
					<settings.postsPerPage>
						<TCEforms>
							<label>postsPerPage</label>
							<config>
								<type>input</type>
								<size>2</size>
								<eval>required, int</eval>
								<default>3</default>
								<!-- PROTECTED REGION ID(flexform.xml.own.config.code.implementation._17_0_2_8a7027a_1315073486092_462354_2359) ENABLED START -->
								<!-- PROTECTED REGION END -->
							</config>
						</TCEforms>
					</settings.postsPerPage>
				</el>
			</ROOT>
		</sDEF>
	</sheets>
</T3DataStructure>
